styvio/__init__.py
styvio-0.0.2.dist-info/LICENSE
styvio-0.0.2.dist-info/METADATA
styvio-0.0.2.dist-info/WHEEL
styvio-0.0.2.dist-info/top_level.txt
styvio-0.0.2.dist-info/RECORD
