Metadata-Version: 2.1
Name: styvio
Version: 0.0.2
Summary: Styvio financial data
Home-page: https://www.Styvio.com/
Author: The Plug Jumbo
Author-email: chnxcx@gmail.com
License: UNKNOWN
Platform: UNKNOWN
Classifier: Programming Language :: Python :: 3
Classifier: License :: OSI Approved :: MIT License
Classifier: Operating System :: OS Independent
Requires-Python: >=3.6
License-File: LICENSE
Requires-Dist: requests
